Metadata-Version: 1.1
Name: ccurl
Version: 0.0.3
Summary: A wrapper around curl to continually curl an endpoint over time
Home-page: https://github.com/dwkerwin/continuous-curl
Author: Doug Kerwin
Author-email: dwkerwin@gmail.com
License: MIT
Keywords: curl,ping
Platform: UNKNOWN
Classifier: Intended Audience :: Developers
Classifier: Natural Language :: English
Classifier: License :: OSI Approved :: MIT License
Classifier: Programming Language :: Python
Classifier: Programming Language :: Python :: 2
Classifier: Programming Language :: Python :: 2.7
Classifier: Programming Language :: Python :: 3
Classifier: Programming Language :: Python :: 3.6
